llama_index/postprocessor/nvidia_rerank/__init__.py
llama_index/postprocessor/nvidia_rerank/base.py
llama_index/postprocessor/nvidia_rerank/utils.py
llama_index_postprocessor_nvidia_rerank-0.5.4.dist-info/METADATA
llama_index_postprocessor_nvidia_rerank-0.5.4.dist-info/WHEEL
llama_index_postprocessor_nvidia_rerank-0.5.4.dist-info/licenses/LICENSE
llama_index_postprocessor_nvidia_rerank-0.5.4.dist-info/RECORD
