Metadata-Version: 2.4
Name: llama-index-postprocessor-nvidia-rerank
Version: 0.5.4
Summary: llama-index postprocessor nvidia_rerank integration
Author-email: Your Name <you@example.com>
License-Expression: MIT
License-File: LICENSE
Requires-Python: <4.0,>=3.9
Requires-Dist: llama-index-core<0.15,>=0.13.0
